mattermost_post_utils/__init__.py
mattermost_post_utils-0.0.6.dist-info/METADATA
mattermost_post_utils-0.0.6.dist-info/WHEEL
mattermost_post_utils-0.0.6.dist-info/top_level.txt
mattermost_post_utils-0.0.6.dist-info/RECORD
