Metadata-Version: 2.1
Name: mattermost-post-utils
Version: 0.0.6
Summary: A small example package
Home-page: https://gitlab.tech.orange/dtrs-security/devops/mattermost-utils
Author: Example Author
Author-email: author@example.com
License: UNKNOWN
Platform: UNKNOWN
Classifier: Programming Language :: Python :: 3
Classifier: License :: OSI Approved :: MIT License
Classifier: Operating System :: OS Independent
Requires-Python: >=3.6
